lex_bot_deploy/__init__.py
lex_bot_deploy/lex_bot_deploy.py
lex_bot_deploy/examples/BookTrip_Export.json
lex_bot_deploy/examples/OrderFlowers_Export.json
lex_bot_deploy/examples/ScheduleAppointment_Export.json
lex_bot_deploy-0.1.10.data/scripts/lex-bot-deploy
lex_bot_deploy-0.1.10.data/scripts/lex-bot-get-schema
lex_bot_deploy-0.1.10.dist-info/AUTHORS.rst
lex_bot_deploy-0.1.10.dist-info/LICENSE
lex_bot_deploy-0.1.10.dist-info/METADATA
lex_bot_deploy-0.1.10.dist-info/WHEEL
lex_bot_deploy-0.1.10.dist-info/top_level.txt
lex_bot_deploy-0.1.10.dist-info/RECORD
