Metadata-Version: 2.1
Name: lex-bot-deploy
Version: 0.1.10
Summary: Lex Bot deployment script and function
Home-page: https://github.com/Schadix/lex_bot_deploy
Author: Martin Schade
Author-email: git.schade@gmail.com
License: MIT license
Keywords: lex-bot-deploy Amazon Lex Deployment automation Schema
Platform: UNKNOWN
Classifier: Development Status :: 2 - Pre-Alpha
Classifier: Intended Audience :: Developers
Classifier: License :: OSI Approved :: MIT License
Classifier: Natural Language :: English
Classifier: Programming Language :: Python :: 2.7
Classifier: Programming Language :: Python :: 3
Classifier: Programming Language :: Python :: 3.4
Classifier: Programming Language :: Python :: 3.5
Classifier: Programming Language :: Python :: 3.6
Classifier: Programming Language :: Python :: 3.7
Requires-Dist: boto3
Requires-Dist: botocore
Requires-Dist: tenacity
